<?xml version="1.0" encoding="utf-8"?>
<Root>
  <Data ID="301" GameID="3" RoomNameType="1" Name="欢乐骰子" RobotGold="400000,800000,1200000,2000000,5000000" GoldWeight="10,15,25,35,15" LifeTime="180" BetRobotCount="10,25" BankerRobotCount="2,9" BankerRobotGold="15000000,25000000" LeaveGold="12000000" />
  <Data ID="302" GameID="3" RoomNameType="2" Name="欢乐骰子" RobotGold="8000,16000,24000,40000,100000" GoldWeight="10,15,25,35,15" LifeTime="180" BetRobotCount="30,60" BankerRobotCount="2,9" BankerRobotGold="1500000,2500000" LeaveGold="200000" />
  <Data ID="303" GameID="3" RoomNameType="3" Name="欢乐骰子" RobotGold="20000,40000,60000,100000,250000" GoldWeight="10,15,25,35,15" LifeTime="180" BetRobotCount="30,45" BankerRobotCount="2,9" BankerRobotGold="3000000,5000000" LeaveGold="500000" />
  <Data ID="304" GameID="3" RoomNameType="4" Name="欢乐骰子" RobotGold="80000,160000,240000,400000,1000000" GoldWeight="10,15,25,35,15" LifeTime="180" BetRobotCount="20,35" BankerRobotCount="2,9" BankerRobotGold="7500000,12500000" LeaveGold="2000000" />
  <Data ID="305" GameID="3" RoomNameType="5" Name="欢乐骰子" RobotGold="400000,800000,1200000,2000000,5000000" GoldWeight="10,15,25,35,15" LifeTime="180" BetRobotCount="10,25" BankerRobotCount="2,9" BankerRobotGold="15000000,25000000" LeaveGold="5000000" />
  <Data ID="401" GameID="4" RoomNameType="1" Name="百人牛牛" RobotGold="40000,80000,120000,200000,500000" GoldWeight="10,15,25,35,15" LifeTime="180" BetRobotCount="10,25" BankerRobotCount="2,9" BankerRobotGold="20000000,40000000" LeaveGold="12000000" />
  <Data ID="402" GameID="4" RoomNameType="2" Name="百人牛牛" RobotGold="800,1600,2400,4000,10000" GoldWeight="10,15,25,35,15" LifeTime="180" BetRobotCount="60,90" BankerRobotCount="2,9" BankerRobotGold="5000000,10000000" LeaveGold="200000" />
  <Data ID="403" GameID="4" RoomNameType="3" Name="百人牛牛" RobotGold="2000,4000,6000,10000,25000" GoldWeight="10,15,25,35,15" LifeTime="180" BetRobotCount="45,80" BankerRobotCount="2,9" BankerRobotGold="10000000,20000000" LeaveGold="500000" />
  <Data ID="404" GameID="4" RoomNameType="4" Name="百人牛牛" RobotGold="8000,16000,24000,40000,100000" GoldWeight="10,15,25,35,15" LifeTime="180" BetRobotCount="30,60" BankerRobotCount="2,9" BankerRobotGold="15000000,30000000" LeaveGold="2000000" />
  <Data ID="405" GameID="4" RoomNameType="5" Name="百人牛牛" RobotGold="40000,80000,120000,200000,500000" GoldWeight="10,15,25,35,15" LifeTime="180" BetRobotCount="20,40" BankerRobotCount="2,9" BankerRobotGold="20000000,40000000" LeaveGold="5000000" />
  <Data ID="501" GameID="5" RoomNameType="1" Name="百家乐" RobotGold="400000,800000,1200000,2000000,5000000" GoldWeight="10,15,25,35,15" LifeTime="180" BetRobotCount="10,25" BankerRobotCount="2,9" BankerRobotGold="15000000,25000000" LeaveGold="12000000" />
  <Data ID="502" GameID="5" RoomNameType="2" Name="百家乐" RobotGold="8000,16000,24000,40000,100000" GoldWeight="10,15,25,35,15" LifeTime="180" BetRobotCount="60,90" BankerRobotCount="2,9" BankerRobotGold="1500000,2500000" LeaveGold="200000" />
  <Data ID="503" GameID="5" RoomNameType="3" Name="百家乐" RobotGold="20000,40000,60000,100000,250000" GoldWeight="10,15,25,35,15" LifeTime="180" BetRobotCount="45,80" BankerRobotCount="2,9" BankerRobotGold="3000000,5000000" LeaveGold="500000" />
  <Data ID="504" GameID="5" RoomNameType="4" Name="百家乐" RobotGold="80000,160000,240000,400000,1000000" GoldWeight="10,15,25,35,15" LifeTime="180" BetRobotCount="30,60" BankerRobotCount="2,9" BankerRobotGold="7500000,12500000" LeaveGold="2000000" />
  <Data ID="505" GameID="5" RoomNameType="5" Name="百家乐" RobotGold="400000,800000,1200000,2000000,5000000" GoldWeight="10,15,25,35,15" LifeTime="180" BetRobotCount="20,40" BankerRobotCount="2,9" BankerRobotGold="15000000,25000000" LeaveGold="5000000" />
  <Data ID="1001" GameID="10" RoomNameType="1" Name="黑红梅方" RobotGold="400000,800000,1200000,2000000,5000000" GoldWeight="10,15,25,35,15" LifeTime="180" BetRobotCount="10,25" BankerRobotCount="2,9" BankerRobotGold="15000000,25000000" LeaveGold="12000000" />
  <Data ID="1002" GameID="10" RoomNameType="2" Name="黑红梅方" RobotGold="8000,16000,24000,40000,100000" GoldWeight="10,15,25,35,15" LifeTime="180" BetRobotCount="30,60" BankerRobotCount="2,9" BankerRobotGold="1500000,2500000" LeaveGold="200000" />
  <Data ID="1003" GameID="10" RoomNameType="3" Name="黑红梅方" RobotGold="20000,40000,60000,100000,250000" GoldWeight="10,15,25,35,15" LifeTime="180" BetRobotCount="30,45" BankerRobotCount="2,9" BankerRobotGold="3000000,5000000" LeaveGold="500000" />
  <Data ID="1004" GameID="10" RoomNameType="4" Name="黑红梅方" RobotGold="80000,160000,240000,400000,1000000" GoldWeight="10,15,25,35,15" LifeTime="180" BetRobotCount="20,35" BankerRobotCount="2,9" BankerRobotGold="7500000,12500000" LeaveGold="2000000" />
  <Data ID="1005" GameID="10" RoomNameType="5" Name="黑红梅方" RobotGold="400000,800000,1200000,2000000,5000000" GoldWeight="10,15,25,35,15" LifeTime="180" BetRobotCount="10,25" BankerRobotCount="2,9" BankerRobotGold="15000000,25000000" LeaveGold="5000000" />
  <Data ID="1201" GameID="12" RoomNameType="1" Name="金鲨银鲨" RobotGold="400000,800000,1200000,2000000,5000000" GoldWeight="10,15,25,35,15" LifeTime="180" BetRobotCount="10,25" BankerRobotCount="2,9" BankerRobotGold="15000000,25000000" LeaveGold="12000000" />
  <Data ID="1202" GameID="12" RoomNameType="2" Name="金鲨银鲨" RobotGold="8000,16000,24000,40000,100000" GoldWeight="10,15,25,35,15" LifeTime="180" BetRobotCount="30,60" BankerRobotCount="2,9" BankerRobotGold="1500000,2500000" LeaveGold="200000" />
  <Data ID="1203" GameID="12" RoomNameType="3" Name="金鲨银鲨" RobotGold="20000,40000,60000,100000,250000" GoldWeight="10,15,25,35,15" LifeTime="180" BetRobotCount="30,45" BankerRobotCount="2,9" BankerRobotGold="3000000,5000000" LeaveGold="500000" />
  <Data ID="1204" GameID="12" RoomNameType="4" Name="金鲨银鲨" RobotGold="80000,160000,240000,400000,1000000" GoldWeight="10,15,25,35,15" LifeTime="180" BetRobotCount="20,35" BankerRobotCount="2,9" BankerRobotGold="7500000,12500000" LeaveGold="2000000" />
  <Data ID="1205" GameID="12" RoomNameType="5" Name="金鲨银鲨" RobotGold="400000,800000,1200000,2000000,5000000" GoldWeight="10,15,25,35,15" LifeTime="180" BetRobotCount="10,25" BankerRobotCount="2,9" BankerRobotGold="15000000,25000000" LeaveGold="5000000" />
  <Data ID="2901" GameID="29" RoomNameType="1" Name="万人德州" RobotGold="40000,80000,120000,200000,500000" GoldWeight="10,15,25,35,15" LifeTime="180" BetRobotCount="10,25" BankerRobotCount="2,9" BankerRobotGold="20000000,40000000" LeaveGold="12000000" />
  <Data ID="2902" GameID="29" RoomNameType="2" Name="万人德州" RobotGold="800,1600,2400,4000,10000" GoldWeight="10,15,25,35,15" LifeTime="180" BetRobotCount="30,60" BankerRobotCount="2,9" BankerRobotGold="5000000,10000000" LeaveGold="200000" />
  <Data ID="2903" GameID="29" RoomNameType="3" Name="万人德州" RobotGold="2000,4000,6000,10000,25000" GoldWeight="10,15,25,35,15" LifeTime="180" BetRobotCount="30,45" BankerRobotCount="2,9" BankerRobotGold="10000000,20000000" LeaveGold="500000" />
  <Data ID="2904" GameID="29" RoomNameType="4" Name="万人德州" RobotGold="8000,16000,24000,40000,100000" GoldWeight="10,15,25,35,15" LifeTime="180" BetRobotCount="20,35" BankerRobotCount="2,9" BankerRobotGold="15000000,30000000" LeaveGold="2000000" />
  <Data ID="2905" GameID="29" RoomNameType="5" Name="万人德州" RobotGold="40000,80000,120000,200000,500000" GoldWeight="10,15,25,35,15" LifeTime="180" BetRobotCount="10,25" BankerRobotCount="2,9" BankerRobotGold="20000000,40000000" LeaveGold="5000000" />
  <Data ID="2601" GameID="26" RoomNameType="1" Name="森林舞会" RobotGold="400000,800000,1200000,2000000,5000000" GoldWeight="10,15,25,35,15" LifeTime="180" BetRobotCount="10,25" BankerRobotCount="0,0" BankerRobotGold="15000000,25000000" LeaveGold="12000000" />
  <Data ID="2602" GameID="26" RoomNameType="2" Name="森林舞会" RobotGold="8000,16000,24000,40000,100000" GoldWeight="10,15,25,35,15" LifeTime="180" BetRobotCount="30,60" BankerRobotCount="0,0" BankerRobotGold="1500000,2500000" LeaveGold="200000" />
  <Data ID="2603" GameID="26" RoomNameType="3" Name="森林舞会" RobotGold="20000,40000,60000,100000,250000" GoldWeight="10,15,25,35,15" LifeTime="180" BetRobotCount="30,45" BankerRobotCount="0,0" BankerRobotGold="3000000,5000000" LeaveGold="500000" />
  <Data ID="2604" GameID="26" RoomNameType="4" Name="森林舞会" RobotGold="80000,160000,240000,400000,1000000" GoldWeight="10,15,25,35,15" LifeTime="180" BetRobotCount="20,35" BankerRobotCount="0,0" BankerRobotGold="7500000,12500000" LeaveGold="2000000" />
  <Data ID="2605" GameID="26" RoomNameType="5" Name="森林舞会" RobotGold="400000,800000,1200000,2000000,5000000" GoldWeight="10,15,25,35,15" LifeTime="180" BetRobotCount="10,25" BankerRobotCount="0,0" BankerRobotGold="15000000,25000000" LeaveGold="5000000" />
  <Data ID="3101" GameID="31" RoomNameType="1" Name="二八杠" RobotGold="400000,800000,1200000,2000000,5000000" GoldWeight="10,15,25,35,15" LifeTime="180" BetRobotCount="10,25" BankerRobotCount="2,9" BankerRobotGold="15000000,25000000" LeaveGold="12000000" />
  <Data ID="3102" GameID="31" RoomNameType="2" Name="二八杠" RobotGold="8000,16000,24000,40000,100000" GoldWeight="10,15,25,35,15" LifeTime="180" BetRobotCount="60,90" BankerRobotCount="2,9" BankerRobotGold="1500000,2500000" LeaveGold="200000" />
  <Data ID="3103" GameID="31" RoomNameType="3" Name="二八杠" RobotGold="20000,40000,60000,100000,250000" GoldWeight="10,15,25,35,15" LifeTime="180" BetRobotCount="45,80" BankerRobotCount="2,9" BankerRobotGold="3000000,5000000" LeaveGold="500000" />
  <Data ID="3104" GameID="31" RoomNameType="4" Name="二八杠" RobotGold="80000,160000,240000,400000,1000000" GoldWeight="10,15,25,35,15" LifeTime="180" BetRobotCount="30,60" BankerRobotCount="2,9" BankerRobotGold="7500000,12500000" LeaveGold="2000000" />
  <Data ID="3105" GameID="31" RoomNameType="5" Name="二八杠" RobotGold="400000,800000,1200000,2000000,5000000" GoldWeight="10,15,25,35,15" LifeTime="180" BetRobotCount="20,40" BankerRobotCount="2,9" BankerRobotGold="15000000,25000000" LeaveGold="5000000" />
  <Data ID="3201" GameID="32" RoomNameType="1" Name="龙虎斗" RobotGold="400000,800000,1200000,2000000,5000000" GoldWeight="10,15,25,35,15" LifeTime="180" BetRobotCount="10,25" BankerRobotCount="2,9" BankerRobotGold="15000000,25000000" LeaveGold="12000000" />
  <Data ID="3202" GameID="32" RoomNameType="2" Name="龙虎斗" RobotGold="8000,16000,24000,40000,100000" GoldWeight="10,15,25,35,15" LifeTime="180" BetRobotCount="60,90" BankerRobotCount="2,9" BankerRobotGold="1500000,2500000" LeaveGold="200000" />
  <Data ID="3203" GameID="32" RoomNameType="3" Name="龙虎斗" RobotGold="20000,40000,60000,100000,250000" GoldWeight="10,15,25,35,15" LifeTime="180" BetRobotCount="45,80" BankerRobotCount="2,9" BankerRobotGold="3000000,5000000" LeaveGold="500000" />
  <Data ID="3204" GameID="32" RoomNameType="4" Name="龙虎斗" RobotGold="80000,160000,240000,400000,1000000" GoldWeight="10,15,25,35,15" LifeTime="180" BetRobotCount="30,60" BankerRobotCount="2,9" BankerRobotGold="7500000,12500000" LeaveGold="2000000" />
  <Data ID="3205" GameID="32" RoomNameType="5" Name="龙虎斗" RobotGold="400000,800000,1200000,2000000,5000000" GoldWeight="10,15,25,35,15" LifeTime="180" BetRobotCount="20,40" BankerRobotCount="2,9" BankerRobotGold="15000000,25000000" LeaveGold="5000000" />
  <Data ID="3701" GameID="37" RoomNameType="1" Name="水果缤纷" RobotGold="400000,800000,1200000,2000000,5000000" GoldWeight="10,15,25,35,15" LifeTime="180" BetRobotCount="10,25" BankerRobotCount="0,0" BankerRobotGold="15000000,25000000" LeaveGold="12000000" />
  <Data ID="3702" GameID="37" RoomNameType="2" Name="水果缤纷" RobotGold="8000,16000,24000,40000,100000" GoldWeight="10,15,25,35,15" LifeTime="180" BetRobotCount="30,60" BankerRobotCount="0,0" BankerRobotGold="1500000,2500000" LeaveGold="200000" />
  <Data ID="3703" GameID="37" RoomNameType="3" Name="水果缤纷" RobotGold="20000,40000,60000,100000,250000" GoldWeight="10,15,25,35,15" LifeTime="180" BetRobotCount="30,45" BankerRobotCount="0,0" BankerRobotGold="3000000,5000000" LeaveGold="500000" />
  <Data ID="3704" GameID="37" RoomNameType="4" Name="水果缤纷" RobotGold="80000,160000,240000,400000,1000000" GoldWeight="10,15,25,35,15" LifeTime="180" BetRobotCount="20,35" BankerRobotCount="0,0" BankerRobotGold="7500000,12500000" LeaveGold="2000000" />
  <Data ID="3705" GameID="37" RoomNameType="5" Name="水果缤纷" RobotGold="400000,800000,1200000,2000000,5000000" GoldWeight="10,15,25,35,15" LifeTime="180" BetRobotCount="10,25" BankerRobotCount="0,0" BankerRobotGold="15000000,25000000" LeaveGold="5000000" />
  <Data ID="3301" GameID="33" RoomNameType="1" Name="一元夺宝" RobotGold="5000000" GoldWeight="100" LifeTime="180" BetRobotCount="10,10" BankerRobotCount="0,0" BankerRobotGold="3000000,7000000" LeaveGold="12000000" />
  <Data ID="3302" GameID="33" RoomNameType="2" Name="一元夺宝" RobotGold="5000000" GoldWeight="100" LifeTime="180" BetRobotCount="10,10" BankerRobotCount="0,0" BankerRobotGold="3000000,7000000" LeaveGold="12000000" />
  <Data ID="3303" GameID="33" RoomNameType="3" Name="一元夺宝" RobotGold="5000000" GoldWeight="100" LifeTime="180" BetRobotCount="10,10" BankerRobotCount="0,0" BankerRobotGold="3000000,7000000" LeaveGold="12000000" />
  <Data ID="3304" GameID="33" RoomNameType="4" Name="一元夺宝" RobotGold="5000000" GoldWeight="100" LifeTime="180" BetRobotCount="10,10" BankerRobotCount="0,0" BankerRobotGold="3000000,7000000" LeaveGold="12000000" />
  <Data ID="3305" GameID="33" RoomNameType="5" Name="一元夺宝" RobotGold="5000000" GoldWeight="100" LifeTime="180" BetRobotCount="10,10" BankerRobotCount="0,0" BankerRobotGold="3000000,7000000" LeaveGold="12000000" />
  <Data ID="3501" GameID="35" RoomNameType="1" Name="推筒子" RobotGold="400000,800000,1200000,2000000,5000000" GoldWeight="10,15,25,35,15" LifeTime="180" BetRobotCount="10,25" BankerRobotCount="0,0" BankerRobotGold="15000000,25000000" LeaveGold="12000000" />
  <Data ID="3502" GameID="35" RoomNameType="2" Name="推筒子" RobotGold="8000,16000,24000,40000,100000" GoldWeight="10,15,25,35,15" LifeTime="180" BetRobotCount="30,60" BankerRobotCount="0,0" BankerRobotGold="1500000,2500000" LeaveGold="200000" />
  <Data ID="3503" GameID="35" RoomNameType="3" Name="推筒子" RobotGold="20000,40000,60000,100000,250000" GoldWeight="10,15,25,35,15" LifeTime="180" BetRobotCount="30,45" BankerRobotCount="0,0" BankerRobotGold="3000000,5000000" LeaveGold="500000" />
  <Data ID="3504" GameID="35" RoomNameType="4" Name="推筒子" RobotGold="80000,160000,240000,400000,1000000" GoldWeight="10,15,25,35,15" LifeTime="180" BetRobotCount="20,35" BankerRobotCount="0,0" BankerRobotGold="7500000,12500000" LeaveGold="2000000" />
  <Data ID="3505" GameID="35" RoomNameType="5" Name="推筒子" RobotGold="400000,800000,1200000,2000000,5000000" GoldWeight="10,15,25,35,15" LifeTime="180" BetRobotCount="10,25" BankerRobotCount="0,0" BankerRobotGold="15000000,25000000" LeaveGold="5000000" />
  <Data ID="2301" GameID="23" RoomNameType="1" Name="奔驰宝马" RobotGold="400000,800000,1200000,2000000,5000000" GoldWeight="10,15,25,35,15" LifeTime="180" BetRobotCount="10,25" BankerRobotCount="2,9" BankerRobotGold="15000000,25000000" LeaveGold="12000000" />
  <Data ID="2302" GameID="23" RoomNameType="2" Name="奔驰宝马" RobotGold="8000,16000,24000,40000,100000" GoldWeight="10,15,25,35,15" LifeTime="180" BetRobotCount="30,60" BankerRobotCount="2,9" BankerRobotGold="1500000,2500000" LeaveGold="200000" />
  <Data ID="2303" GameID="23" RoomNameType="3" Name="奔驰宝马" RobotGold="20000,40000,60000,100000,250000" GoldWeight="10,15,25,35,15" LifeTime="180" BetRobotCount="30,45" BankerRobotCount="2,9" BankerRobotGold="3000000,5000000" LeaveGold="500000" />
  <Data ID="2304" GameID="23" RoomNameType="4" Name="奔驰宝马" RobotGold="80000,160000,240000,400000,1000000" GoldWeight="10,15,25,35,15" LifeTime="180" BetRobotCount="20,35" BankerRobotCount="2,9" BankerRobotGold="7500000,12500000" LeaveGold="2000000" />
  <Data ID="2305" GameID="23" RoomNameType="5" Name="奔驰宝马" RobotGold="400000,800000,1200000,2000000,5000000" GoldWeight="10,15,25,35,15" LifeTime="180" BetRobotCount="10,25" BankerRobotCount="2,9" BankerRobotGold="15000000,25000000" LeaveGold="5000000" />
  <Data ID="4001" GameID="40" RoomNameType="1" Name="百人红黑" RobotGold="400000,800000,1200000,2000000,5000000" GoldWeight="10,15,25,35,15" LifeTime="180" BetRobotCount="10,25" BankerRobotCount="0,0" BankerRobotGold="15000000,25000000" LeaveGold="12000000" />
  <Data ID="4002" GameID="40" RoomNameType="2" Name="百人红黑" RobotGold="8000,16000,24000,40000,100000" GoldWeight="10,15,25,35,15" LifeTime="180" BetRobotCount="30,60" BankerRobotCount="0,0" BankerRobotGold="1500000,2500000" LeaveGold="200000" />
  <Data ID="4003" GameID="40" RoomNameType="3" Name="百人红黑" RobotGold="20000,40000,60000,100000,250000" GoldWeight="10,15,25,35,15" LifeTime="180" BetRobotCount="30,45" BankerRobotCount="0,0" BankerRobotGold="3000000,5000000" LeaveGold="500000" />
  <Data ID="4004" GameID="40" RoomNameType="4" Name="百人红黑" RobotGold="80000,160000,240000,400000,1000000" GoldWeight="10,15,25,35,15" LifeTime="180" BetRobotCount="20,35" BankerRobotCount="0,0" BankerRobotGold="7500000,12500000" LeaveGold="2000000" />
  <Data ID="4005" GameID="40" RoomNameType="5" Name="百人红黑" RobotGold="400000,800000,1200000,2000000,5000000" GoldWeight="10,15,25,35,15" LifeTime="180" BetRobotCount="10,25" BankerRobotCount="0,0" BankerRobotGold="15000000,25000000" LeaveGold="5000000" />
  <Data ID="1401" GameID="14" RoomNameType="1" Name="欢乐至尊" RobotGold="400000,800000,1200000,2000000,5000000" GoldWeight="10,15,25,35,15" LifeTime="180" BetRobotCount="10,25" BankerRobotCount="2,9" BankerRobotGold="15000000,25000000" LeaveGold="12000000" />
  <Data ID="1402" GameID="14" RoomNameType="2" Name="欢乐至尊" RobotGold="8000,16000,24000,40000,100000" GoldWeight="10,15,25,35,15" LifeTime="180" BetRobotCount="30,60" BankerRobotCount="2,9" BankerRobotGold="1500000,2500000" LeaveGold="200000" />
  <Data ID="1403" GameID="14" RoomNameType="3" Name="欢乐至尊" RobotGold="20000,40000,60000,100000,250000" GoldWeight="10,15,25,35,15" LifeTime="180" BetRobotCount="30,45" BankerRobotCount="2,9" BankerRobotGold="3000000,5000000" LeaveGold="500000" />
  <Data ID="1404" GameID="14" RoomNameType="4" Name="欢乐至尊" RobotGold="80000,160000,240000,400000,1000000" GoldWeight="10,15,25,35,15" LifeTime="180" BetRobotCount="20,35" BankerRobotCount="2,9" BankerRobotGold="7500000,12500000" LeaveGold="2000000" />
  <Data ID="1405" GameID="14" RoomNameType="5" Name="欢乐至尊" RobotGold="400000,800000,1200000,2000000,5000000" GoldWeight="10,15,25,35,15" LifeTime="180" BetRobotCount="10,25" BankerRobotCount="2,9" BankerRobotGold="15000000,25000000" LeaveGold="5000000" />
  <Data ID="5201" GameID="52" RoomNameType="1" Name="四色球" RobotGold="400000,800000,1200000,2000000,5000000" GoldWeight="10,15,25,35,15" LifeTime="180" BetRobotCount="10,25" BankerRobotCount="0,0" BankerRobotGold="15000000,25000000" LeaveGold="12000000" />
  <Data ID="5202" GameID="52" RoomNameType="2" Name="四色球" RobotGold="8000,16000,24000,40000,100000" GoldWeight="10,15,25,35,15" LifeTime="180" BetRobotCount="30,60" BankerRobotCount="0,0" BankerRobotGold="1500000,2500000" LeaveGold="200000" />
  <Data ID="5203" GameID="52" RoomNameType="3" Name="四色球" RobotGold="20000,40000,60000,100000,250000" GoldWeight="10,15,25,35,15" LifeTime="180" BetRobotCount="30,45" BankerRobotCount="0,0" BankerRobotGold="3000000,5000000" LeaveGold="500000" />
  <Data ID="5204" GameID="52" RoomNameType="4" Name="四色球" RobotGold="80000,160000,240000,400000,1000000" GoldWeight="10,15,25,35,15" LifeTime="180" BetRobotCount="20,35" BankerRobotCount="0,0" BankerRobotGold="7500000,12500000" LeaveGold="2000000" />
  <Data ID="5205" GameID="52" RoomNameType="5" Name="四色球" RobotGold="400000,800000,1200000,2000000,5000000" GoldWeight="10,15,25,35,15" LifeTime="180" BetRobotCount="10,25" BankerRobotCount="0,0" BankerRobotGold="15000000,25000000" LeaveGold="5000000" />
  <Data ID="5301" GameID="53" RoomNameType="1" Name="豪车大亨" RobotGold="400000,800000,1200000,2000000,5000000" GoldWeight="10,15,25,35,15" LifeTime="180" BetRobotCount="10,25" BankerRobotCount="2,9" BankerRobotGold="15000000,25000000" LeaveGold="12000000" />
  <Data ID="5302" GameID="53" RoomNameType="2" Name="豪车大亨" RobotGold="8000,16000,24000,40000,100000" GoldWeight="10,15,25,35,15" LifeTime="180" BetRobotCount="30,60" BankerRobotCount="2,9" BankerRobotGold="1500000,2500000" LeaveGold="200000" />
  <Data ID="5303" GameID="53" RoomNameType="3" Name="豪车大亨" RobotGold="20000,40000,60000,100000,250000" GoldWeight="10,15,25,35,15" LifeTime="180" BetRobotCount="30,45" BankerRobotCount="2,9" BankerRobotGold="3000000,5000000" LeaveGold="500000" />
  <Data ID="5304" GameID="53" RoomNameType="4" Name="豪车大亨" RobotGold="80000,160000,240000,400000,1000000" GoldWeight="10,15,25,35,15" LifeTime="180" BetRobotCount="20,35" BankerRobotCount="2,9" BankerRobotGold="7500000,12500000" LeaveGold="2000000" />
  <Data ID="5305" GameID="53" RoomNameType="5" Name="豪车大亨" RobotGold="400000,800000,1200000,2000000,5000000" GoldWeight="10,15,25,35,15" LifeTime="180" BetRobotCount="10,25" BankerRobotCount="2,9" BankerRobotGold="15000000,25000000" LeaveGold="5000000" />
  <Data ID="5701" GameID="57" RoomNameType="1" Name="英雄联盟时时彩" RobotGold="400000,800000,1200000,2000000,5000000" GoldWeight="10,15,25,35,15" LifeTime="180" BetRobotCount="10,25" BankerRobotCount="0,0" BankerRobotGold="15000000,25000000" LeaveGold="12000000" />
  <Data ID="5702" GameID="57" RoomNameType="2" Name="英雄联盟时时彩" RobotGold="8000,16000,24000,40000,100000" GoldWeight="10,15,25,35,15" LifeTime="180" BetRobotCount="30,60" BankerRobotCount="0,0" BankerRobotGold="1500000,2500000" LeaveGold="200000" />
  <Data ID="5703" GameID="57" RoomNameType="3" Name="英雄联盟时时彩" RobotGold="20000,40000,60000,100000,250000" GoldWeight="10,15,25,35,15" LifeTime="180" BetRobotCount="30,45" BankerRobotCount="0,0" BankerRobotGold="3000000,5000000" LeaveGold="500000" />
  <Data ID="5704" GameID="57" RoomNameType="4" Name="英雄联盟时时彩" RobotGold="80000,160000,240000,400000,1000000" GoldWeight="10,15,25,35,15" LifeTime="180" BetRobotCount="20,35" BankerRobotCount="0,0" BankerRobotGold="7500000,12500000" LeaveGold="2000000" />
  <Data ID="5705" GameID="57" RoomNameType="5" Name="英雄联盟时时彩" RobotGold="400000,800000,1200000,2000000,5000000" GoldWeight="10,15,25,35,15" LifeTime="180" BetRobotCount="10,25" BankerRobotCount="0,0" BankerRobotGold="15000000,25000000" LeaveGold="5000000" />
  <Data ID="5901" GameID="59" RoomNameType="1" Name="斗牛" RobotGold="400000,800000,1200000,2000000,5000000" GoldWeight="10,15,25,35,15" LifeTime="180" BetRobotCount="10,25" BankerRobotCount="0,0" BankerRobotGold="15000000,25000000" LeaveGold="12000000" />
  <Data ID="5902" GameID="59" RoomNameType="2" Name="斗牛" RobotGold="8000,16000,24000,40000,100000" GoldWeight="10,15,25,35,15" LifeTime="180" BetRobotCount="30,60" BankerRobotCount="0,0" BankerRobotGold="1500000,2500000" LeaveGold="200000" />
  <Data ID="5903" GameID="59" RoomNameType="3" Name="斗牛" RobotGold="20000,40000,60000,100000,250000" GoldWeight="10,15,25,35,15" LifeTime="180" BetRobotCount="30,45" BankerRobotCount="0,0" BankerRobotGold="3000000,5000000" LeaveGold="500000" />
  <Data ID="5904" GameID="59" RoomNameType="4" Name="斗牛" RobotGold="80000,160000,240000,400000,1000000" GoldWeight="10,15,25,35,15" LifeTime="180" BetRobotCount="20,35" BankerRobotCount="0,0" BankerRobotGold="7500000,12500000" LeaveGold="2000000" />
  <Data ID="5905" GameID="59" RoomNameType="5" Name="斗牛" RobotGold="400000,800000,1200000,2000000,5000000" GoldWeight="10,15,25,35,15" LifeTime="180" BetRobotCount="10,25" BankerRobotCount="0,0" BankerRobotGold="15000000,25000000" LeaveGold="5000000" />
  <Data ID="6101" GameID="61" RoomNameType="1" Name="神兽之战" RobotGold="80000,160000,240000,400000,1000000" GoldWeight="10,15,25,35,15" LifeTime="180" BetRobotCount="10,25" BankerRobotCount="2,9" BankerRobotGold="20000000,40000000" LeaveGold="12000000" />
  <Data ID="6102" GameID="61" RoomNameType="2" Name="神兽之战" RobotGold="1600,3200,4800,8000,20000" GoldWeight="10,15,25,35,15" LifeTime="180" BetRobotCount="30,60" BankerRobotCount="2,9" BankerRobotGold="5000000,10000000" LeaveGold="200000" />
  <Data ID="6103" GameID="61" RoomNameType="3" Name="神兽之战" RobotGold="4000,8000,12000,20000,50000" GoldWeight="10,15,25,35,15" LifeTime="180" BetRobotCount="30,45" BankerRobotCount="2,9" BankerRobotGold="10000000,20000000" LeaveGold="500000" />
  <Data ID="6104" GameID="61" RoomNameType="4" Name="神兽之战" RobotGold="16000,32000,48000,80000,200000" GoldWeight="10,15,25,35,15" LifeTime="180" BetRobotCount="20,35" BankerRobotCount="2,9" BankerRobotGold="15000000,30000000" LeaveGold="2000000" />
  <Data ID="6105" GameID="61" RoomNameType="5" Name="神兽之战" RobotGold="80000,160000,240000,400000,1000000" GoldWeight="10,15,25,35,15" LifeTime="180" BetRobotCount="10,25" BankerRobotCount="2,9" BankerRobotGold="20000000,40000000" LeaveGold="5000000" />
  <Data ID="6201" GameID="62" RoomNameType="1" Name="百人三公" RobotGold="40000,80000,120000,200000,500000" GoldWeight="10,15,25,35,15" LifeTime="180" BetRobotCount="10,25" BankerRobotCount="2,9" BankerRobotGold="20000000,40000000" LeaveGold="12000000" />
  <Data ID="6202" GameID="62" RoomNameType="2" Name="百人三公" RobotGold="800,1600,2400,4000,10000" GoldWeight="10,15,25,35,15" LifeTime="180" BetRobotCount="30,60" BankerRobotCount="2,9" BankerRobotGold="5000000,10000000" LeaveGold="200000" />
  <Data ID="6203" GameID="62" RoomNameType="3" Name="百人三公" RobotGold="2000,4000,6000,10000,25000" GoldWeight="10,15,25,35,15" LifeTime="180" BetRobotCount="30,45" BankerRobotCount="2,9" BankerRobotGold="10000000,20000000" LeaveGold="500000" />
  <Data ID="6204" GameID="62" RoomNameType="4" Name="百人三公" RobotGold="8000,16000,24000,40000,100000" GoldWeight="10,15,25,35,15" LifeTime="180" BetRobotCount="20,35" BankerRobotCount="2,9" BankerRobotGold="15000000,30000000" LeaveGold="2000000" />
  <Data ID="6205" GameID="62" RoomNameType="5" Name="百人三公" RobotGold="40000,80000,120000,200000,500000" GoldWeight="10,15,25,35,15" LifeTime="180" BetRobotCount="10,25" BankerRobotCount="2,9" BankerRobotGold="20000000,40000000" LeaveGold="5000000" />
  <Data ID="6401" GameID="64" RoomNameType="1" Name="德州牛仔" RobotGold="400000,800000,1200000,2000000,5000000" GoldWeight="10,15,25,35,15" LifeTime="180" BetRobotCount="10,25" BankerRobotCount="0,0" BankerRobotGold="15000000,25000000" LeaveGold="12000000" />
  <Data ID="6402" GameID="64" RoomNameType="2" Name="德州牛仔" RobotGold="8000,16000,24000,40000,100000" GoldWeight="10,15,25,35,15" LifeTime="180" BetRobotCount="30,60" BankerRobotCount="0,0" BankerRobotGold="1500000,2500000" LeaveGold="200000" />
  <Data ID="6403" GameID="64" RoomNameType="3" Name="德州牛仔" RobotGold="20000,40000,60000,100000,250000" GoldWeight="10,15,25,35,15" LifeTime="180" BetRobotCount="30,45" BankerRobotCount="0,0" BankerRobotGold="3000000,5000000" LeaveGold="500000" />
  <Data ID="6404" GameID="64" RoomNameType="4" Name="德州牛仔" RobotGold="80000,160000,240000,400000,1000000" GoldWeight="10,15,25,35,15" LifeTime="180" BetRobotCount="20,35" BankerRobotCount="0,0" BankerRobotGold="7500000,12500000" LeaveGold="2000000" />
  <Data ID="6405" GameID="64" RoomNameType="5" Name="德州牛仔" RobotGold="400000,800000,1200000,2000000,5000000" GoldWeight="10,15,25,35,15" LifeTime="180" BetRobotCount="10,25" BankerRobotCount="0,0" BankerRobotGold="15000000,25000000" LeaveGold="5000000" />
  <Data ID="7201" GameID="72" RoomNameType="1" Name="万条筒" RobotGold="400000,800000,1200000,2000000,5000000" GoldWeight="10,15,25,35,15" LifeTime="180" BetRobotCount="10,25" BankerRobotCount="0,0" BankerRobotGold="15000000,25000000" LeaveGold="12000000" />
  <Data ID="7202" GameID="72" RoomNameType="2" Name="万条筒" RobotGold="8000,16000,24000,40000,100000" GoldWeight="10,15,25,35,15" LifeTime="180" BetRobotCount="30,60" BankerRobotCount="0,0" BankerRobotGold="1500000,2500000" LeaveGold="200000" />
  <Data ID="7203" GameID="72" RoomNameType="3" Name="万条筒" RobotGold="20000,40000,60000,100000,250000" GoldWeight="10,15,25,35,15" LifeTime="180" BetRobotCount="30,45" BankerRobotCount="0,0" BankerRobotGold="3000000,5000000" LeaveGold="500000" />
  <Data ID="7204" GameID="72" RoomNameType="4" Name="万条筒" RobotGold="80000,160000,240000,400000,1000000" GoldWeight="10,15,25,35,15" LifeTime="180" BetRobotCount="20,35" BankerRobotCount="0,0" BankerRobotGold="7500000,12500000" LeaveGold="2000000" />
  <Data ID="7205" GameID="72" RoomNameType="5" Name="万条筒" RobotGold="400000,800000,1200000,2000000,5000000" GoldWeight="10,15,25,35,15" LifeTime="180" BetRobotCount="10,25" BankerRobotCount="0,0" BankerRobotGold="15000000,25000000" LeaveGold="5000000" />
  <Data ID="7301" GameID="73" RoomNameType="1" Name="斗三公" RobotGold="400000,800000,1200000,2000000,5000000" GoldWeight="10,15,25,35,15" LifeTime="180" BetRobotCount="10,25" BankerRobotCount="0,0" BankerRobotGold="15000000,25000000" LeaveGold="12000000" />
  <Data ID="7302" GameID="73" RoomNameType="2" Name="斗三公" RobotGold="8000,16000,24000,40000,100000" GoldWeight="10,15,25,35,15" LifeTime="180" BetRobotCount="30,60" BankerRobotCount="0,0" BankerRobotGold="1500000,2500000" LeaveGold="200000" />
  <Data ID="7303" GameID="73" RoomNameType="3" Name="斗三公" RobotGold="20000,40000,60000,100000,250000" GoldWeight="10,15,25,35,15" LifeTime="180" BetRobotCount="30,45" BankerRobotCount="0,0" BankerRobotGold="3000000,5000000" LeaveGold="500000" />
  <Data ID="7304" GameID="73" RoomNameType="4" Name="斗三公" RobotGold="80000,160000,240000,400000,1000000" GoldWeight="10,15,25,35,15" LifeTime="180" BetRobotCount="20,35" BankerRobotCount="0,0" BankerRobotGold="7500000,12500000" LeaveGold="2000000" />
  <Data ID="7305" GameID="73" RoomNameType="5" Name="斗三公" RobotGold="400000,800000,1200000,2000000,5000000" GoldWeight="10,15,25,35,15" LifeTime="180" BetRobotCount="10,25" BankerRobotCount="0,0" BankerRobotGold="15000000,25000000" LeaveGold="5000000" />
  <Data ID="7501" GameID="75" RoomNameType="1" Name="牌九" RobotGold="400000,800000,1200000,2000000,5000000" GoldWeight="10,15,25,35,15" LifeTime="180" BetRobotCount="10,25" BankerRobotCount="2,9" BankerRobotGold="15000000,25000000" LeaveGold="12000000" />
  <Data ID="7502" GameID="75" RoomNameType="2" Name="牌九" RobotGold="8000,16000,24000,40000,100000" GoldWeight="10,15,25,35,15" LifeTime="180" BetRobotCount="30,60" BankerRobotCount="2,9" BankerRobotGold="1500000,2500000" LeaveGold="200000" />
  <Data ID="7503" GameID="75" RoomNameType="3" Name="牌九" RobotGold="20000,40000,60000,100000,250000" GoldWeight="10,15,25,35,15" LifeTime="180" BetRobotCount="30,45" BankerRobotCount="2,9" BankerRobotGold="3000000,5000000" LeaveGold="500000" />
  <Data ID="7504" GameID="75" RoomNameType="4" Name="牌九" RobotGold="80000,160000,240000,400000,1000000" GoldWeight="10,15,25,35,15" LifeTime="180" BetRobotCount="20,35" BankerRobotCount="2,9" BankerRobotGold="7500000,12500000" LeaveGold="2000000" />
  <Data ID="7505" GameID="75" RoomNameType="5" Name="牌九" RobotGold="400000,800000,1200000,2000000,5000000" GoldWeight="10,15,25,35,15" LifeTime="180" BetRobotCount="10,25" BankerRobotCount="2,9" BankerRobotGold="15000000,25000000" LeaveGold="5000000" />
  <Data ID="7901" GameID="79" RoomNameType="1" Name="龙虎猜和" RobotGold="400000,800000,1200000,2000000,5000000" GoldWeight="10,15,25,35,15" LifeTime="180" BetRobotCount="10,25" BankerRobotCount="0,0" BankerRobotGold="15000000,25000000" LeaveGold="12000000" />
  <Data ID="7902" GameID="79" RoomNameType="2" Name="龙虎猜和" RobotGold="8000,16000,24000,40000,100000" GoldWeight="10,15,25,35,15" LifeTime="180" BetRobotCount="30,60" BankerRobotCount="0,0" BankerRobotGold="1500000,2500000" LeaveGold="200000" />
  <Data ID="7903" GameID="79" RoomNameType="3" Name="龙虎猜和" RobotGold="20000,40000,60000,100000,250000" GoldWeight="10,15,25,35,15" LifeTime="180" BetRobotCount="30,45" BankerRobotCount="0,0" BankerRobotGold="3000000,5000000" LeaveGold="500000" />
  <Data ID="7904" GameID="79" RoomNameType="4" Name="龙虎猜和" RobotGold="80000,160000,240000,400000,1000000" GoldWeight="10,15,25,35,15" LifeTime="180" BetRobotCount="20,35" BankerRobotCount="0,0" BankerRobotGold="7500000,12500000" LeaveGold="2000000" />
  <Data ID="7905" GameID="79" RoomNameType="5" Name="龙虎猜和" RobotGold="400000,800000,1200000,2000000,5000000" GoldWeight="10,15,25,35,15" LifeTime="180" BetRobotCount="10,25" BankerRobotCount="0,0" BankerRobotGold="15000000,25000000" LeaveGold="5000000" />
  <Data ID="8101" GameID="81" RoomNameType="1" Name="福星推筒子" RobotGold="400000,800000,1200000,2000000,5000000" GoldWeight="10,15,25,35,15" LifeTime="180" BetRobotCount="10,25" BankerRobotCount="0,0" BankerRobotGold="15000000,25000000" LeaveGold="12000000" />
  <Data ID="8102" GameID="81" RoomNameType="2" Name="福星推筒子" RobotGold="8000,16000,24000,40000,100000" GoldWeight="10,15,25,35,15" LifeTime="180" BetRobotCount="30,60" BankerRobotCount="0,0" BankerRobotGold="1500000,2500000" LeaveGold="200000" />
  <Data ID="8103" GameID="81" RoomNameType="3" Name="福星推筒子" RobotGold="20000,40000,60000,100000,250000" GoldWeight="10,15,25,35,15" LifeTime="180" BetRobotCount="30,45" BankerRobotCount="0,0" BankerRobotGold="3000000,5000000" LeaveGold="500000" />
  <Data ID="8104" GameID="81" RoomNameType="4" Name="福星推筒子" RobotGold="80000,160000,240000,400000,1000000" GoldWeight="10,15,25,35,15" LifeTime="180" BetRobotCount="20,35" BankerRobotCount="0,0" BankerRobotGold="7500000,12500000" LeaveGold="2000000" />
  <Data ID="8105" GameID="81" RoomNameType="5" Name="福星推筒子" RobotGold="400000,800000,1200000,2000000,5000000" GoldWeight="10,15,25,35,15" LifeTime="180" BetRobotCount="10,25" BankerRobotCount="0,0" BankerRobotGold="15000000,25000000" LeaveGold="5000000" />
  <Data ID="8201" GameID="82" RoomNameType="1" Name="赌神推牌九" RobotGold="400000,800000,1200000,2000000,5000000" GoldWeight="10,15,25,35,15" LifeTime="180" BetRobotCount="10,25" BankerRobotCount="0,0" BankerRobotGold="15000000,25000000" LeaveGold="12000000" />
  <Data ID="8202" GameID="82" RoomNameType="2" Name="赌神推牌九" RobotGold="8000,16000,24000,40000,100000" GoldWeight="10,15,25,35,15" LifeTime="180" BetRobotCount="30,60" BankerRobotCount="0,0" BankerRobotGold="1500000,2500000" LeaveGold="200000" />
  <Data ID="8203" GameID="82" RoomNameType="3" Name="赌神推牌九" RobotGold="20000,40000,60000,100000,250000" GoldWeight="10,15,25,35,15" LifeTime="180" BetRobotCount="30,45" BankerRobotCount="0,0" BankerRobotGold="3000000,5000000" LeaveGold="500000" />
  <Data ID="8204" GameID="82" RoomNameType="4" Name="赌神推牌九" RobotGold="80000,160000,240000,400000,1000000" GoldWeight="10,15,25,35,15" LifeTime="180" BetRobotCount="20,35" BankerRobotCount="0,0" BankerRobotGold="7500000,12500000" LeaveGold="2000000" />
  <Data ID="8205" GameID="82" RoomNameType="5" Name="赌神推牌九" RobotGold="400000,800000,1200000,2000000,5000000" GoldWeight="10,15,25,35,15" LifeTime="180" BetRobotCount="10,25" BankerRobotCount="0,0" BankerRobotGold="15000000,25000000" LeaveGold="5000000" />
  <Data ID="8301" GameID="83" RoomNameType="1" Name="鱼虾蟹" RobotGold="400000,800000,1200000,2000000,5000000" GoldWeight="10,15,25,35,15" LifeTime="180" BetRobotCount="10,25" BankerRobotCount="0,0" BankerRobotGold="15000000,25000000" LeaveGold="12000000" />
  <Data ID="8302" GameID="83" RoomNameType="2" Name="鱼虾蟹" RobotGold="8000,16000,24000,40000,100000" GoldWeight="10,15,25,35,15" LifeTime="180" BetRobotCount="30,60" BankerRobotCount="0,0" BankerRobotGold="1500000,2500000" LeaveGold="200000" />
  <Data ID="8303" GameID="83" RoomNameType="3" Name="鱼虾蟹" RobotGold="20000,40000,60000,100000,250000" GoldWeight="10,15,25,35,15" LifeTime="180" BetRobotCount="30,45" BankerRobotCount="0,0" BankerRobotGold="3000000,5000000" LeaveGold="500000" />
  <Data ID="8304" GameID="83" RoomNameType="4" Name="鱼虾蟹" RobotGold="80000,160000,240000,400000,1000000" GoldWeight="10,15,25,35,15" LifeTime="180" BetRobotCount="20,35" BankerRobotCount="0,0" BankerRobotGold="7500000,12500000" LeaveGold="2000000" />
  <Data ID="8305" GameID="83" RoomNameType="5" Name="鱼虾蟹" RobotGold="400000,800000,1200000,2000000,5000000" GoldWeight="10,15,25,35,15" LifeTime="180" BetRobotCount="10,25" BankerRobotCount="0,0" BankerRobotGold="15000000,25000000" LeaveGold="5000000" />
  <Data ID="8501" GameID="85" RoomNameType="1" Name="幸运7" RobotGold="400000,800000,1200000,2000000,5000000" GoldWeight="10,15,25,35,15" LifeTime="180" BetRobotCount="10,25" BankerRobotCount="0,0" BankerRobotGold="15000000,25000000" LeaveGold="12000000" />
  <Data ID="8502" GameID="85" RoomNameType="2" Name="幸运7" RobotGold="8000,16000,24000,40000,100000" GoldWeight="10,15,25,35,15" LifeTime="180" BetRobotCount="30,60" BankerRobotCount="0,0" BankerRobotGold="1500000,2500000" LeaveGold="200000" />
  <Data ID="8503" GameID="85" RoomNameType="3" Name="幸运7" RobotGold="20000,40000,60000,100000,250000" GoldWeight="10,15,25,35,15" LifeTime="180" BetRobotCount="30,45" BankerRobotCount="0,0" BankerRobotGold="3000000,5000000" LeaveGold="500000" />
  <Data ID="8504" GameID="85" RoomNameType="4" Name="幸运7" RobotGold="80000,160000,240000,400000,1000000" GoldWeight="10,15,25,35,15" LifeTime="180" BetRobotCount="20,35" BankerRobotCount="0,0" BankerRobotGold="7500000,12500000" LeaveGold="2000000" />
  <Data ID="8505" GameID="85" RoomNameType="5" Name="幸运7" RobotGold="400000,800000,1200000,2000000,5000000" GoldWeight="10,15,25,35,15" LifeTime="180" BetRobotCount="10,25" BankerRobotCount="0,0" BankerRobotGold="15000000,25000000" LeaveGold="5000000" />
  <Data ID="8401" GameID="84" RoomNameType="1" Name="竟眯百家乐" RobotGold="400000,800000,1200000,2000000,5000000" GoldWeight="10,15,25,35,15" LifeTime="180" BetRobotCount="10,25" BankerRobotCount="0,0" BankerRobotGold="15000000,25000000" LeaveGold="12000000" />
  <Data ID="8402" GameID="84" RoomNameType="2" Name="竟眯百家乐" RobotGold="8000,16000,24000,40000,100000" GoldWeight="10,15,25,35,15" LifeTime="180" BetRobotCount="30,60" BankerRobotCount="0,0" BankerRobotGold="1500000,2500000" LeaveGold="200000" />
  <Data ID="8403" GameID="84" RoomNameType="3" Name="竟眯百家乐" RobotGold="20000,40000,60000,100000,250000" GoldWeight="10,15,25,35,15" LifeTime="180" BetRobotCount="30,45" BankerRobotCount="0,0" BankerRobotGold="3000000,5000000" LeaveGold="500000" />
  <Data ID="8404" GameID="84" RoomNameType="4" Name="竟眯百家乐" RobotGold="80000,160000,240000,400000,1000000" GoldWeight="10,15,25,35,15" LifeTime="180" BetRobotCount="20,35" BankerRobotCount="0,0" BankerRobotGold="7500000,12500000" LeaveGold="2000000" />
  <Data ID="8405" GameID="84" RoomNameType="5" Name="竟眯百家乐" RobotGold="400000,800000,1200000,2000000,5000000" GoldWeight="10,15,25,35,15" LifeTime="180" BetRobotCount="10,25" BankerRobotCount="0,0" BankerRobotGold="15000000,25000000" LeaveGold="5000000" />
  <Data ID="9601" GameID="96" RoomNameType="1" Name="王者时时彩" RobotGold="400000,800000,1200000,2000000,5000000" GoldWeight="10,15,25,35,15" LifeTime="180" BetRobotCount="10,25" BankerRobotCount="0,0" BankerRobotGold="15000000,25000000" LeaveGold="12000000" />
  <Data ID="9602" GameID="96" RoomNameType="2" Name="王者时时彩" RobotGold="8000,16000,24000,40000,100000" GoldWeight="10,15,25,35,15" LifeTime="180" BetRobotCount="30,60" BankerRobotCount="0,0" BankerRobotGold="1500000,2500000" LeaveGold="200000" />
  <Data ID="9603" GameID="96" RoomNameType="3" Name="王者时时彩" RobotGold="20000,40000,60000,100000,250000" GoldWeight="10,15,25,35,15" LifeTime="180" BetRobotCount="30,45" BankerRobotCount="0,0" BankerRobotGold="3000000,5000000" LeaveGold="500000" />
  <Data ID="9604" GameID="96" RoomNameType="4" Name="王者时时彩" RobotGold="80000,160000,240000,400000,1000000" GoldWeight="10,15,25,35,15" LifeTime="180" BetRobotCount="20,35" BankerRobotCount="0,0" BankerRobotGold="7500000,12500000" LeaveGold="2000000" />
  <Data ID="9605" GameID="96" RoomNameType="5" Name="王者时时彩" RobotGold="400000,800000,1200000,2000000,5000000" GoldWeight="10,15,25,35,15" LifeTime="180" BetRobotCount="10,25" BankerRobotCount="0,0" BankerRobotGold="15000000,25000000" LeaveGold="5000000" />
  <Data ID="9701" GameID="97" RoomNameType="1" Name="群雄逐鹿" RobotGold="400000,800000,1200000,2000000,5000000" GoldWeight="10,15,25,35,15" LifeTime="180" BetRobotCount="10,25" BankerRobotCount="0,0" BankerRobotGold="15000000,25000000" LeaveGold="12000000" />
  <Data ID="9702" GameID="97" RoomNameType="2" Name="群雄逐鹿" RobotGold="8000,16000,24000,40000,100000" GoldWeight="10,15,25,35,15" LifeTime="180" BetRobotCount="30,60" BankerRobotCount="0,0" BankerRobotGold="1500000,2500000" LeaveGold="200000" />
  <Data ID="9703" GameID="97" RoomNameType="3" Name="群雄逐鹿" RobotGold="20000,40000,60000,100000,250000" GoldWeight="10,15,25,35,15" LifeTime="180" BetRobotCount="30,45" BankerRobotCount="0,0" BankerRobotGold="3000000,5000000" LeaveGold="500000" />
  <Data ID="9704" GameID="97" RoomNameType="4" Name="群雄逐鹿" RobotGold="80000,160000,240000,400000,1000000" GoldWeight="10,15,25,35,15" LifeTime="180" BetRobotCount="20,35" BankerRobotCount="0,0" BankerRobotGold="7500000,12500000" LeaveGold="2000000" />
  <Data ID="9705" GameID="97" RoomNameType="5" Name="群雄逐鹿" RobotGold="400000,800000,1200000,2000000,5000000" GoldWeight="10,15,25,35,15" LifeTime="180" BetRobotCount="10,25" BankerRobotCount="0,0" BankerRobotGold="15000000,25000000" LeaveGold="5000000" />
  <Data ID="10101" GameID="101" RoomNameType="1" Name="DOTA时时彩" RobotGold="400000,800000,1200000,2000000,5000000" GoldWeight="10,15,25,35,15" LifeTime="180" BetRobotCount="10,25" BankerRobotCount="0,0" BankerRobotGold="15000000,25000000" LeaveGold="12000000" />
  <Data ID="10102" GameID="101" RoomNameType="2" Name="DOTA时时彩" RobotGold="8000,16000,24000,40000,100000" GoldWeight="10,15,25,35,15" LifeTime="180" BetRobotCount="30,60" BankerRobotCount="0,0" BankerRobotGold="1500000,2500000" LeaveGold="200000" />
  <Data ID="10103" GameID="101" RoomNameType="3" Name="DOTA时时彩" RobotGold="20000,40000,60000,100000,250000" GoldWeight="10,15,25,35,15" LifeTime="180" BetRobotCount="30,45" BankerRobotCount="0,0" BankerRobotGold="3000000,5000000" LeaveGold="500000" />
  <Data ID="10104" GameID="101" RoomNameType="4" Name="DOTA时时彩" RobotGold="80000,160000,240000,400000,1000000" GoldWeight="10,15,25,35,15" LifeTime="180" BetRobotCount="20,35" BankerRobotCount="0,0" BankerRobotGold="7500000,12500000" LeaveGold="2000000" />
  <Data ID="10105" GameID="101" RoomNameType="5" Name="DOTA时时彩" RobotGold="400000,800000,1200000,2000000,5000000" GoldWeight="10,15,25,35,15" LifeTime="180" BetRobotCount="10,25" BankerRobotCount="0,0" BankerRobotGold="15000000,25000000" LeaveGold="5000000" />
  <Data ID="14301" GameID="143" RoomNameType="1" Name="射龙门" RobotGold="400000,800000,1200000,2000000,5000000" GoldWeight="10,15,25,35,15" LifeTime="180" BetRobotCount="10,25" BankerRobotCount="0,0" BankerRobotGold="15000000,25000000" LeaveGold="12000000" />
  <Data ID="14302" GameID="143" RoomNameType="2" Name="射龙门" RobotGold="8000,16000,24000,40000,100000" GoldWeight="10,15,25,35,15" LifeTime="180" BetRobotCount="30,60" BankerRobotCount="0,0" BankerRobotGold="1500000,2500000" LeaveGold="200000" />
  <Data ID="14303" GameID="143" RoomNameType="3" Name="射龙门" RobotGold="20000,40000,60000,100000,250000" GoldWeight="10,15,25,35,15" LifeTime="180" BetRobotCount="30,45" BankerRobotCount="0,0" BankerRobotGold="3000000,5000000" LeaveGold="500000" />
  <Data ID="14304" GameID="143" RoomNameType="4" Name="射龙门" RobotGold="80000,160000,240000,400000,1000000" GoldWeight="10,15,25,35,15" LifeTime="180" BetRobotCount="20,35" BankerRobotCount="0,0" BankerRobotGold="7500000,12500000" LeaveGold="2000000" />
  <Data ID="14305" GameID="143" RoomNameType="5" Name="射龙门" RobotGold="400000,800000,1200000,2000000,5000000" GoldWeight="10,15,25,35,15" LifeTime="180" BetRobotCount="10,25" BankerRobotCount="0,0" BankerRobotGold="15000000,25000000" LeaveGold="5000000" />
  <Data ID="14401" GameID="144" RoomNameType="1" Name="暴雪全家桶" RobotGold="400000,800000,1200000,2000000,5000000" GoldWeight="10,15,25,35,15" LifeTime="180" BetRobotCount="10,25" BankerRobotCount="0,0" BankerRobotGold="15000000,25000000" LeaveGold="12000000" />
  <Data ID="14402" GameID="144" RoomNameType="2" Name="暴雪全家桶" RobotGold="8000,16000,24000,40000,100000" GoldWeight="10,15,25,35,15" LifeTime="180" BetRobotCount="30,60" BankerRobotCount="0,0" BankerRobotGold="1500000,2500000" LeaveGold="200000" />
  <Data ID="14403" GameID="144" RoomNameType="3" Name="暴雪全家桶" RobotGold="20000,40000,60000,100000,250000" GoldWeight="10,15,25,35,15" LifeTime="180" BetRobotCount="30,45" BankerRobotCount="0,0" BankerRobotGold="3000000,5000000" LeaveGold="500000" />
  <Data ID="14404" GameID="144" RoomNameType="4" Name="暴雪全家桶" RobotGold="80000,160000,240000,400000,1000000" GoldWeight="10,15,25,35,15" LifeTime="180" BetRobotCount="20,35" BankerRobotCount="0,0" BankerRobotGold="7500000,12500000" LeaveGold="2000000" />
  <Data ID="14405" GameID="144" RoomNameType="5" Name="暴雪全家桶" RobotGold="400000,800000,1200000,2000000,5000000" GoldWeight="10,15,25,35,15" LifeTime="180" BetRobotCount="10,25" BankerRobotCount="0,0" BankerRobotGold="15000000,25000000" LeaveGold="5000000" />
  <Data ID="14601" GameID="146" RoomNameType="1" Name="三国时时彩" RobotGold="400000,800000,1200000,2000000,5000000" GoldWeight="10,15,25,35,15" LifeTime="180" BetRobotCount="10,25" BankerRobotCount="0,0" BankerRobotGold="15000000,25000000" LeaveGold="12000000" />
  <Data ID="14602" GameID="146" RoomNameType="2" Name="三国时时彩" RobotGold="8000,16000,24000,40000,100000" GoldWeight="10,15,25,35,15" LifeTime="180" BetRobotCount="30,60" BankerRobotCount="0,0" BankerRobotGold="1500000,2500000" LeaveGold="200000" />
  <Data ID="14603" GameID="146" RoomNameType="3" Name="三国时时彩" RobotGold="20000,40000,60000,100000,250000" GoldWeight="10,15,25,35,15" LifeTime="180" BetRobotCount="30,45" BankerRobotCount="0,0" BankerRobotGold="3000000,5000000" LeaveGold="500000" />
  <Data ID="14604" GameID="146" RoomNameType="4" Name="三国时时彩" RobotGold="80000,160000,240000,400000,1000000" GoldWeight="10,15,25,35,15" LifeTime="180" BetRobotCount="20,35" BankerRobotCount="0,0" BankerRobotGold="7500000,12500000" LeaveGold="2000000" />
  <Data ID="14605" GameID="146" RoomNameType="5" Name="三国时时彩" RobotGold="400000,800000,1200000,2000000,5000000" GoldWeight="10,15,25,35,15" LifeTime="180" BetRobotCount="10,25" BankerRobotCount="0,0" BankerRobotGold="15000000,25000000" LeaveGold="5000000" />
  <Data ID="14701" GameID="147" RoomNameType="1" Name="水浒时时彩" RobotGold="400000,800000,1200000,2000000,5000000" GoldWeight="10,15,25,35,15" LifeTime="180" BetRobotCount="10,25" BankerRobotCount="0,0" BankerRobotGold="15000000,25000000" LeaveGold="12000000" />
  <Data ID="14702" GameID="147" RoomNameType="2" Name="水浒时时彩" RobotGold="8000,16000,24000,40000,100000" GoldWeight="10,15,25,35,15" LifeTime="180" BetRobotCount="30,60" BankerRobotCount="0,0" BankerRobotGold="1500000,2500000" LeaveGold="200000" />
  <Data ID="14703" GameID="147" RoomNameType="3" Name="水浒时时彩" RobotGold="20000,40000,60000,100000,250000" GoldWeight="10,15,25,35,15" LifeTime="180" BetRobotCount="30,45" BankerRobotCount="0,0" BankerRobotGold="3000000,5000000" LeaveGold="500000" />
  <Data ID="14704" GameID="147" RoomNameType="4" Name="水浒时时彩" RobotGold="80000,160000,240000,400000,1000000" GoldWeight="10,15,25,35,15" LifeTime="180" BetRobotCount="20,35" BankerRobotCount="0,0" BankerRobotGold="7500000,12500000" LeaveGold="2000000" />
  <Data ID="14705" GameID="147" RoomNameType="5" Name="水浒时时彩" RobotGold="400000,800000,1200000,2000000,5000000" GoldWeight="10,15,25,35,15" LifeTime="180" BetRobotCount="10,25" BankerRobotCount="0,0" BankerRobotGold="15000000,25000000" LeaveGold="5000000" />
  <Data ID="20201" GameID="202" RoomNameType="1" Name="竞咪红黑大战" RobotGold="400000,800000,1200000,2000000,5000000" GoldWeight="10,15,25,35,15" LifeTime="180" BetRobotCount="10,25" BankerRobotCount="0,0" BankerRobotGold="15000000,25000000" LeaveGold="12000000" />
  <Data ID="20202" GameID="202" RoomNameType="2" Name="竞咪红黑大战" RobotGold="8000,16000,24000,40000,100000" GoldWeight="10,15,25,35,15" LifeTime="180" BetRobotCount="30,60" BankerRobotCount="0,0" BankerRobotGold="1500000,2500000" LeaveGold="200000" />
  <Data ID="20203" GameID="202" RoomNameType="3" Name="竞咪红黑大战" RobotGold="20000,40000,60000,100000,250000" GoldWeight="10,15,25,35,15" LifeTime="180" BetRobotCount="30,45" BankerRobotCount="0,0" BankerRobotGold="3000000,5000000" LeaveGold="500000" />
  <Data ID="20204" GameID="202" RoomNameType="4" Name="竞咪红黑大战" RobotGold="80000,160000,240000,400000,1000000" GoldWeight="10,15,25,35,15" LifeTime="180" BetRobotCount="20,35" BankerRobotCount="0,0" BankerRobotGold="7500000,12500000" LeaveGold="2000000" />
  <Data ID="20205" GameID="202" RoomNameType="5" Name="竞咪红黑大战" RobotGold="400000,800000,1200000,2000000,5000000" GoldWeight="10,15,25,35,15" LifeTime="180" BetRobotCount="10,25" BankerRobotCount="0,0" BankerRobotGold="15000000,25000000" LeaveGold="5000000" />
</Root>